tapioca_trello/__init__.py
tapioca_trello/tapioca_trello.py
tapioca_trello/resource_mapping/__init__.py
tapioca_trello/resource_mapping/action.py
tapioca_trello/resource_mapping/batch.py
tapioca_trello/resource_mapping/board.py
tapioca_trello/resource_mapping/card.py
tapioca_trello/resource_mapping/checklist.py
tapioca_trello/resource_mapping/custom_field.py
tapioca_trello/resource_mapping/enterprise.py
tapioca_trello/resource_mapping/label.py
tapioca_trello/resource_mapping/lane.py
tapioca_trello/resource_mapping/member.py
tapioca_trello/resource_mapping/notification.py
tapioca_trello/resource_mapping/organization.py
tapioca_trello/resource_mapping/search.py
tapioca_trello/resource_mapping/token.py
tapioca_trello/resource_mapping/webhook.py
tapioca_trello-0.5.dist-info/METADATA
tapioca_trello-0.5.dist-info/RECORD
tapioca_trello-0.5.dist-info/WHEEL
tapioca_trello-0.5.dist-info/top_level.txt
tests/__init__.py
tests/test_tapioca_trello.py
